[{
    "name": "contra",
    "url": "./images/Contra.jpg"
  },
  {
    "name": "dance",
    "url": "./images/dancecentral.jpg"
  },
  {
    "name": "donkeykong",
    "url": "./images/Donkeykong.jpg"
  },
  {
    "name": "duckhunt",
    "url": "./images/duckhunt.jpg"
  },
  {
    "name": "sonic",
    "url": "./images/sonic.jpg"
  },
  {
    "name": "mario",
    "url": "./images/mario.jpg"
  },
  {
    "name": "drmario",
    "url": "./images/drmario.jpg"
  },
  {
    "name": "ken",
    "url": "./images/ken.jpg"
  },
  {
    "name": "ryu",
    "url": "./images/ryu.jpg"
  },
  {
    "name": "vega",
    "url": "./images/vega.jpg"
  },
  {
    "name": "zelda",
    "url": "./images/zelda.jpg"
  },
  {
    "name": "scorpion",
    "url": "./images/scorpion.jpg"
  }]